yta_general/__init__.py
yta_general/dataclasses.py
yta_general-0.0.9.dist-info/LICENSE
yta_general-0.0.9.dist-info/METADATA
yta_general-0.0.9.dist-info/WHEEL
yta_general-0.0.9.dist-info/RECORD
